agreement_phi/__init__.py
agreement_phi-0.3.0.dist-info/METADATA
agreement_phi-0.3.0.dist-info/RECORD
agreement_phi-0.3.0.dist-info/WHEEL
agreement_phi-0.3.0.dist-info/entry_points.txt
agreement_phi-0.3.0.dist-info/top_level.txt
