Metadata-Version: 2.1
Name: agreement-phi
Version: 0.3.0
Summary: Inter-rater agreement Phi, as an alternative to Kripperndorfs alpha, as described in https://github.com/AlessandroChecco/agreement-phi
Home-page: https://github.com/AlessandroChecco/agreement-phi
Author: Alessandro Checco
Author-email: a.checco@sheffield.ac.uk
License: UNKNOWN
Project-URL: Bug Reports, https://github.com/AlessandroChecco/agreement-phi/issues
Project-URL: Source, https://github.com/AlessandroChecco/agreement-phi
Keywords: agreement krippendorff
Platform: UNKNOWN
Classifier: Development Status :: 3 - Alpha
Classifier: Intended Audience :: Science/Research
Classifier: Topic :: Scientific/Engineering :: Information Analysis
Classifier: License :: OSI Approved :: MIT License
Classifier: Programming Language :: Python :: 3
Provides-Extra: test
Provides-Extra: dev
Requires-Dist: pymc3 (>=3.3)
Provides-Extra: dev
Requires-Dist: check-manifest; extra == 'dev'
Provides-Extra: test
Requires-Dist: coverage; extra == 'test'
